eido/__init__.py
eido/__main__.py
eido/_version.py
eido/argparser.py
eido/cli.py
eido/const.py
eido/conversion.py
eido/conversion_plugins.py
eido/exceptions.py
eido/inspection.py
eido/output_formatters.py
eido/schema.py
eido/validation.py
eido-0.2.4.dist-info/LICENSE.txt
eido-0.2.4.dist-info/METADATA
eido-0.2.4.dist-info/WHEEL
eido-0.2.4.dist-info/entry_points.txt
eido-0.2.4.dist-info/top_level.txt
eido-0.2.4.dist-info/RECORD
