Metadata-Version: 2.1
Name: eido
Version: 0.2.4
Summary: A project metadata validator
Home-page: https://github.com/pepkit/eido/
Author: Michal Stolarczyk, Nathan Sheffield
License: BSD2
Keywords: project,metadata,bioinformatics,sequencing,ngs,workflow
Classifier: Development Status :: 4 - Beta
Classifier: License :: OSI Approved :: BSD License
Classifier: Programming Language :: Python :: 3.8
Classifier: Programming Language :: Python :: 3.9
Classifier: Programming Language :: Python :: 3.10
Classifier: Programming Language :: Python :: 3.11
Classifier: Topic :: Scientific/Engineering :: Bio-Informatics
License-File: LICENSE.txt
Requires-Dist: importlib-metadata; python_version < "3.10"
Requires-Dist: jsonschema>=3.0.1
Requires-Dist: logmuse>=0.2.5
Requires-Dist: pandas
Requires-Dist: peppy>=0.40.7
Requires-Dist: ubiquerg>=0.5.2
